clip/__init__.py
clip/bpe_simple_vocab_16e6.txt.gz
clip/model.py
clip/tokenizer.py
paddleclip-1.0.0.dist-info/LICENSE
paddleclip-1.0.0.dist-info/METADATA
paddleclip-1.0.0.dist-info/WHEEL
paddleclip-1.0.0.dist-info/top_level.txt
paddleclip-1.0.0.dist-info/RECORD
